occamtools/__init__.py
occamtools/fort5_to_xyz.py
occamtools/generate_fort5.py
occamtools/occam_data.py
occamtools/read_fort1.py
occamtools/read_fort7.py
occamtools/read_xyz.py
occamtools/xyz_to_fort5.py
occamtools-0.0.1.dist-info/LICENCE
occamtools-0.0.1.dist-info/METADATA
occamtools-0.0.1.dist-info/WHEEL
occamtools-0.0.1.dist-info/top_level.txt
occamtools-0.0.1.dist-info/RECORD
