Metadata-Version: 2.1
Name: occamtools
Version: 0.0.1
Summary: Analysis and synthesis tools for OCCAM hPF simulations
Home-page: https://github.com/mortele/OccamTools
Author: Morten Ledum
Author-email: morten.ledum@gmail.com
License: GPL-3
Platform: UNKNOWN
Classifier: Development Status :: 3 - Alpha
Classifier: License :: OSI Approved :: GNU General Public License v3 (GPLv3)
Classifier: Programming Language :: Python
Classifier: Programming Language :: Python :: 3 :: Only
Classifier: Programming Language :: Python :: 3.7
Requires-Python: >=3.7
Requires-Dist: pytest (>=4.3.0)
Requires-Dist: pytest-cov (>=2.6.1)
Requires-Dist: scikit-learn (>=0.20.2)
Requires-Dist: scipy (>=1.2.1)
Requires-Dist: numpy (>=1.16.1)
Requires-Dist: numba (>=0.42.1)
Requires-Dist: matplotlib (>=3.0.2)
Requires-Dist: flake8 (>=3.7.7)
Requires-Dist: coverage (>=4.5.2)
Requires-Dist: tqdm (>=4.31.1)
